typewraps/__init__.py
typewraps/__main__.py
typewraps-0.0.0.dist-info/LICENSE.txt
typewraps-0.0.0.dist-info/METADATA
typewraps-0.0.0.dist-info/WHEEL
typewraps-0.0.0.dist-info/top_level.txt
typewraps-0.0.0.dist-info/RECORD
