Metadata-Version: 2.1
Name: typewraps
Version: 0.0.0
Summary: typewraps
Author-email: Johannes <johannes-computer@mailfence.com>
License: The MIT License (MIT)
Project-URL: Download, https://pypi.org/project/typewraps/#files
Project-URL: Source, https://github.com/johannes-computer/typewraps
Classifier: License :: OSI Approved :: MIT License
Classifier: Programming Language :: Python
Classifier: Programming Language :: Python :: 3
Requires-Python: >=3.11
License-File: LICENSE.txt
